[{"source":"1","sourceHandle":null,"target":"2","targetHandle":null,"id":"reactflow__edge-1-2"},{"source":"1","sourceHandle":null,"target":"4","targetHandle":null,"id":"reactflow__edge-1-4"},{"source":"2","sourceHandle":null,"target":"10","targetHandle":null,"id":"reactflow__edge-2-10"},{"source":"2","sourceHandle":null,"target":"9","targetHandle":null,"id":"reactflow__edge-2-9"},{"source":"2","sourceHandle":null,"target":"11","targetHandle":null,"id":"reactflow__edge-2-11"},{"source":"2","sourceHandle":null,"target":"12","targetHandle":null,"id":"reactflow__edge-2-12"},{"style":{"strokeWidth":2,"stroke":"#9ca8b3"},"type":"smoothstep","markerEnd":{"type":"arrowclosed"},"source":"3","sourceHandle":"4","target":"7","targetHandle":"1","id":"reactflow__edge-34-71","selected":false},{"style":{"strokeWidth":2,"stroke":"#9ca8b3"},"type":"smoothstep","markerEnd":{"type":"arrowclosed"},"source":"1","sourceHandle":"4","target":"3","targetHandle":"1","id":"reactflow__edge-14-31"},{"style":{"strokeWidth":2,"stroke":"#9ca8b3"},"type":"smoothstep","markerEnd":{"type":"arrowclosed"},"source":"3","sourceHandle":"4","target":"8","targetHandle":"1","id":"reactflow__edge-34-81"},{"style":{"strokeWidth":2,"stroke":"#9ca8b3"},"type":"smoothstep","markerEnd":{"type":"arrowclosed"},"source":"3","sourceHandle":"4","target":"6","targetHandle":"1","id":"reactflow__edge-34-61"},{"style":{"strokeWidth":2,"stroke":"#9ca8b3"},"type":"smoothstep","markerEnd":{"type":"arrowclosed"},"source":"13","sourceHandle":"8","target":"14","targetHandle":"5","id":"reactflow__edge-138-145"},{"style":{"strokeWidth":2,"stroke":"#9ca8b3"},"type":"smoothstep","markerEnd":{"type":"arrowclosed"},"source":"17","sourceHandle":"8","target":"16","targetHandle":"7","id":"reactflow__edge-178-167","selected":false},{"style":{"strokeWidth":2,"stroke":"#9ca8b3"},"type":"smoothstep","markerEnd":{"type":"arrowclosed"},"source":"17","sourceHandle":"4","target":"16","targetHandle":"1","id":"reactflow__edge-174-161"}]