[{"id":"1","type":"custom","data":{"d":"1","name":"Seni seviyorum","level":"Sonsuz","skill":"Yok","desc":"pathladik\nIyi geceler bebegim\n","type":"Premses","source":"Pembe"},"position":{"x":-219.5,"y":-608.5},"width":320,"height":150,"selected":false,"positionAbsolute":{"x":-219.5,"y":-608.5},"dragging":false},{"id":"2","type":"custom","data":{"d":"2","name":"Martial","level":"0","skill":"-","desc":"-","type":"Path","source":"-"},"position":{"x":-640.0676501118131,"y":-968.371498591952},"width":320,"height":150,"selected":false,"positionAbsolute":{"x":-640.0676501118131,"y":-968.371498591952},"dragging":false},{"id":"3","type":"custom","data":{"d":"3","name":"Mage","level":"0","skill":"-","desc":"-","type":"Path","source":"-"},"position":{"x":-210.69182963958605,"y":-248.0637248280293},"width":320,"height":150,"selected":false,"positionAbsolute":{"x":-210.69182963958605,"y":-248.0637248280293},"dragging":false},{"id":"4","type":"custom","data":{"d":"4","name":"Channeler","level":"0","skill":"-","desc":"-","type":"Path","source":"-"},"position":{"x":535.8547267643452,"y":-1060.6314172059272},"width":320,"height":150,"selected":false,"positionAbsolute":{"x":535.8547267643452,"y":-1060.6314172059272},"dragging":false},{"id":"6","type":"custom","data":{"d":"6","name":"Psychic","level":"0","skill":"-","desc":"-","type":"Path","source":"-"},"position":{"x":1375,"y":440},"width":320,"height":150,"selected":false,"positionAbsolute":{"x":1375,"y":440},"dragging":false},{"id":"7","type":"custom","data":{"d":"7","name":"Magic","level":"0","skill":"-","desc":"-","type":"Path","source":"-"},"position":{"x":-275,"y":440},"width":320,"height":150,"selected":false,"positionAbsolute":{"x":-275,"y":440},"dragging":false},{"id":"7","type":"custom","data":{"d":"7","name":"Magic","level":"0","skill":"-","desc":"-","type":"Path","source":"-"},"position":{"x":-275,"y":440},"width":320,"height":150,"selected":false,"positionAbsolute":{"x":-275,"y":440},"dragging":false},{"id":"8","type":"custom","data":{"d":"8","name":"Spirit","level":"0","skill":"-","desc":"-","type":"Path","source":"-"},"position":{"x":-1650,"y":440},"width":320,"height":150,"selected":false,"positionAbsolute":{"x":-1650,"y":440},"dragging":false},{"id":"9","type":"custom","data":{"d":"9","name":"Chi","level":"0","skill":"-","desc":"-","type":"Path","source":"-"},"position":{"x":-1349.0000000000002,"y":-1178},"width":320,"height":150,"selected":false,"positionAbsolute":{"x":-1349.0000000000002,"y":-1178},"dragging":false},{"id":"10","type":"custom","data":{"d":"10","name":"Aura","level":"0","skill":"-","desc":"-","type":"Path","source":"-"},"position":{"x":-2155.6100159655725,"y":-1008.1885987981248},"width":320,"height":150,"selected":false,"positionAbsolute":{"x":-2155.6100159655725,"y":-1008.1885987981248},"dragging":false},{"id":"11","type":"custom","data":{"d":"11","name":"Form","level":"0","skill":"-","desc":"-","type":"Path","source":"-"},"position":{"x":-1485,"y":-1430},"width":320,"height":150,"selected":false,"positionAbsolute":{"x":-1485,"y":-1430},"dragging":false},{"id":"12","type":"custom","data":{"d":"12","name":"Combat","level":"0","skill":"-","desc":"-","type":"Path","source":"-"},"position":{"x":-946,"y":-612},"width":320,"height":150,"selected":false,"positionAbsolute":{"x":-946,"y":-612},"dragging":false},{"id":"13","type":"sticky","data":{"d":"13","desc":"<p><br></p>"},"position":{"x":770,"y":-275},"width":150,"height":22,"selected":false,"positionAbsolute":{"x":770,"y":-275},"dragging":false},{"id":"14","type":"sticky","data":{"d":"14","desc":"<p><br></p>"},"position":{"x":1237.8438025996438,"y":-326.69142597486655},"width":150,"height":22,"selected":false,"positionAbsolute":{"x":1237.8438025996438,"y":-326.69142597486655},"dragging":false},{"id":"16","type":"custom","data":{"d":"16","name":"Extra Attack (2)","level":"11","skill":"Extra Attack (1), Extra Attack (1)","desc":"You can attack twice, instead of once, whenever you take the Attack action on your turn.","type":"MARTIAL","source":"FIGHTER"},"position":{"x":-3080,"y":-165},"width":320,"height":150,"selected":false,"positionAbsolute":{"x":-3080,"y":-165},"dragging":false},{"id":"16","type":"custom","data":{"d":"16","name":"Extra Attack (2)","level":"11","skill":"Extra Attack (1), Extra Attack (1)","desc":"You can attack twice, instead of once, whenever you take the Attack action on your turn.","type":"MARTIAL","source":"FIGHTER"},"position":{"x":-3080,"y":-165},"width":320,"height":150,"selected":false,"positionAbsolute":{"x":-3080,"y":-165},"dragging":false},{"id":"17","type":"custom","data":{"d":"17","name":"Extra Attack (1)","level":"5","skill":"Extra Attack (2)","desc":"You can attack twice, instead of once, whenever you take the Attack action on your turn.","type":"MARTIAL","source":"FIGHTER"},"position":{"x":-3190,"y":-495},"width":320,"height":150,"selected":false,"positionAbsolute":{"x":-3190,"y":-495},"dragging":false},{"id":"18","type":"custom","data":{"d":"18","name":"-","level":"0","skill":"-","desc":"-","type":"-","source":"-"},"position":{"x":-579.999999999998,"y":138.99999999999977},"width":320,"height":150,"selected":false,"positionAbsolute":{"x":-579.999999999998,"y":138.99999999999977},"dragging":false},{"id":"19","type":"sticky","data":{"d":"19","desc":" "},"position":{"x":464.27183141122794,"y":150.6262473168744},"width":150,"height":22,"selected":false,"positionAbsolute":{"x":464.27183141122794,"y":150.6262473168744},"dragging":false},{"id":"20","type":"custom","data":{"d":"20","name":"-","level":"0","skill":"-","desc":"-","type":"-","source":"-"},"position":{"x":711.9258537117262,"y":-441.8417852366107},"width":320,"height":150,"selected":false,"positionAbsolute":{"x":711.9258537117262,"y":-441.8417852366107},"dragging":false},{"id":"22","type":"custom","data":{"d":"22","name":"-","level":"0","skill":"-","desc":"-","type":"-","source":"-"},"position":{"x":83.3815718949457,"y":142.7605619625736},"width":320,"height":150,"selected":false,"positionAbsolute":{"x":83.3815718949457,"y":142.7605619625736},"dragging":false},{"id":"23","type":"custom","data":{"d":"23","name":"-","level":"0","skill":"-","desc":"-","type":"-","source":"-"},"position":{"x":550.0322693152992,"y":-119.05185420978296},"width":320,"height":150,"selected":false,"positionAbsolute":{"x":550.0322693152992,"y":-119.05185420978296},"dragging":false},{"id":"24","type":"sticky","data":{"d":"24","desc":" "},"position":{"x":754,"y":78},"width":150,"height":22},{"id":"25","type":"sticky","data":{"d":"25","desc":" "},"position":{"x":742,"y":84},"width":150,"height":22},{"id":"26","type":"custom","data":{"d":"26","name":"-","level":"0","skill":"-","desc":"-","type":"-","source":"-"},"position":{"x":365.4982128523316,"y":-170.1554385708465},"width":320,"height":150,"selected":false,"positionAbsolute":{"x":365.4982128523316,"y":-170.1554385708465},"dragging":false},{"id":"28","type":"custom","data":{"d":"28","name":"-","level":"0","skill":"-","desc":"-","type":"-","source":"-"},"position":{"x":532.5877808637936,"y":-874.970964899419},"width":320,"height":150,"selected":false,"positionAbsolute":{"x":532.5877808637936,"y":-874.970964899419},"dragging":false},{"id":"30","type":"sticky","data":{"d":"30","desc":" "},"position":{"x":1198,"y":93},"width":150,"height":22},{"id":"31","type":"sticky","data":{"d":"31","desc":" "},"position":{"x":1198,"y":93},"width":150,"height":22},{"id":"32","type":"sticky","data":{"d":"32","desc":" "},"position":{"x":1198,"y":93},"width":150,"height":22},{"id":"33","type":"custom","data":{"d":"33","name":"-","level":"0","skill":"-","desc":"-","type":"-","source":"-"},"position":{"x":1194,"y":50},"width":320,"height":150},{"id":"34","type":"custom","data":{"d":"34","name":"-","level":"0","skill":"-","desc":"-","type":"-","source":"-"},"position":{"x":1194,"y":50},"width":320,"height":150},{"id":"35","type":"custom","data":{"d":"35","name":"-","level":"0","skill":"-","desc":"-","type":"-","source":"-"},"position":{"x":1194,"y":50},"width":320,"height":150},{"id":"36","type":"custom","data":{"d":"36","name":"-","level":"0","skill":"-","desc":"-","type":"-","source":"-"},"position":{"x":1194,"y":50},"width":320,"height":150}]